telegraph2star/__init__.py
telegraph2star/graph4j/__init__.py
telegraph2star/graph4j/graph4j.py
telegraph2star/shell/__init__.py
telegraph2star/shell/usage.py
telegraph2star/src/temp.txt
telegraph4j/__init__.py
telegraph4j/shell/__init__.py
telegraph4j/shell/usage.py
telegraph4j/src/__init__.py
telegraph4j/src/graph4j.py
telegraph4j/src/temp.txt
telegraph4j-0.0.2.dist-info/LICENSE
telegraph4j-0.0.2.dist-info/METADATA
telegraph4j-0.0.2.dist-info/WHEEL
telegraph4j-0.0.2.dist-info/entry_points.txt
telegraph4j-0.0.2.dist-info/top_level.txt
telegraph4j-0.0.2.dist-info/zip-safe
telegraph4j-0.0.2.dist-info/RECORD
